Workbook

Sheet Summary and charts

Sheet Inputs
B2: Discount rate | C2: 0.09
B3: Inflation rate | C3: 0.03 | F3: Cites | G3: New York | I3: Years Horizon | J3: 15
B4: Tax rate (NY) | C4: 0.35 | G4: Hong Kong | J4: 25
B5: Tax rate (HK) | C5: 0
B6: Project start year | C6: 2001
B7: City | C7: New York | E7: TAXATIOn
B8: Horizon | C8: 15
B10: Ship Cost | C10: 39000000
B11: Payment schedule
B12: Y1 | C12: 0.1
B13: Y2 | C13: 0.1
B14: Y3 | C14: 0.8
B15: Initial Working Capital | C15: 500000
B16: WC growth = | C16: Inflation
B17: Scrap value (Y15) | C17: 5000000
B19: Effective tax rate formula | C19: =IF(C7="New York", 35%,0%) -> 0.35

Sheet Rates & Ops
B2: Year | C2: Age | D2: Expected daily hire rate | E2: Operating days | F2: Daily operating Cost | G2: Operating cost | H2: .
B3: 2001
B4: 2002
B5: 2003 | C5: 1 | D5: 20000 | E5: =365 - IF(C3<=5,8,IF(C3<=10,12,16)) -> 357 | F5: 4000 | G5: =F5*365 -> 1460000
B6: 2004 | C6: 2 | D6: 20200 | E6: 358 | F6: =F5*(1+0.03)*(1+0.01) -> 4161.2 | G6: =F6*366 -> 1522999.2 | H6: leap year
B7: 2005 | C7: 3 | D7: 20400 | E7: =365 - IF(C5<=5,8,IF(C5<=10,12,16)) -> 357 | F7: =F6*(1+0.03)*(1+0.01) -> 4328.8964 | G7: =F7*365 -> 1580047.2
B8: 2006 | C8: 4 | D8: 18714 | E8: =365 - IF(C6<=5,8,IF(C6<=10,12,16)) -> 357 | F8: =F7*(1+0.03)*(1+0.01) -> 4503.3509 | G8: =F8*365 -> 1643723.1
B9: 2007 | C9: 5 | D9: 17283 | E9: =365 - IF(C7<=5,8,IF(C7<=10,12,16)) -> 357 | F9: =F8*(1+0.03)*(1+0.01) -> 4684.8359 | G9: =F9*365 -> 1709965.1
B10: 2008 | C10: 6 | D10: 17481 | E10: 354 | F10: =F9*(1+0.03)*(1+0.01) -> 4873.6348 | G10: =F10*366 -> 1783750.3 | H10: leap year
B11: 2009 | C11: 7 | D11: 17682 | E11: 353 | F11: =F10*(1+0.03)*(1+0.01) -> 5070.0423 | G11: =F11*365 -> 1850565.4
B12: 2010 | C12: 8 | D12: 17886 | E12: =365 - IF(C10<=5,8,IF(C10<=10,12,16)) -> 353 | F12: =F11*(1+0.03)*(1+0.01) -> 5274.365 | G12: =F12*365 -> 1925143.2
B13: 2011 | C13: 9 | D13: 18092 | E13: =365 - IF(C11<=5,8,IF(C11<=10,12,16)) -> 353 | F13: =F12*(1+0.03)*(1+0.01) -> 5486.9219 | G13: =F13*365 -> 2002726.5
B14: 2012 | C14: 10 | D14: 17428 | E14: 354 | F14: =F13*(1+0.03)*(1+0.01) -> 5708.0449 | G14: =F14*366 -> 2089144.4 | H14: leap year
B15: 2013 | C15: 11 | D15: 17628 | E15: 349 | F15: =F14*(1+0.03)*(1+0.01) -> 5938.0791 | G15: =F15*365 -> 2167398.9
B16: 2014 | C16: 12 | D16: 17831 | E16: 349 | F16: =F15*(1+0.03)*(1+0.01) -> 6177.3837 | G16: =F16*365 -> 2254745
B17: 2015 | C17: 13 | D17: 18036 | E17: =365 - IF(C15<=5,8,IF(C15<=10,12,16)) -> 349 | F17: =F16*(1+0.03)*(1+0.01) -> 6426.3322 | G17: =F17*365 -> 2345611.3
B18: 2016 | C18: 14 | D18: 18243 | E18: 350 | F18: =F17*(1+0.03)*(1+0.01) -> 6685.3134 | G18: =F18*366 -> 2446824.7 | H18: leap year
B19: 2017 | C19: 15 | D19: 14762 | E19: =365 - IF(C17<=5,8,IF(C17<=10,12,16)) -> 349 | F19: =F18*(1+0.03)*(1+0.01) -> 6954.7315 | G19: =F19*365 -> 2538477
B20: 2018 | C20: 16 | D20: 14932 | E20: =365 - IF(C18<=5,8,IF(C18<=10,12,16)) -> 349 | F20: =F19*(1+0.03)*(1+0.01) -> 7235.0072 | G20: =F20*365 -> 2640777.6
B21: 2019 | C21: 17 | D21: 15104 | E21: =365 - IF(C19<=5,8,IF(C19<=10,12,16)) -> 349 | F21: =F20*(1+0.03)*(1+0.01) -> 7526.578 | G21: =F21*365 -> 2747201
B22: 2020 | C22: 18 | D22: 15278 | E22: 350 | F22: =F21*(1+0.03)*(1+0.01) -> 7829.8991 | G22: =F22*366 -> 2865743.1 | H22: leap year
B23: 2021 | C23: 19 | D23: 15454 | E23: =365 - IF(C21<=5,8,IF(C21<=10,12,16)) -> 349 | F23: =F22*(1+0.03)*(1+0.01) -> 8145.444 | G23: =F23*365 -> 2973087.1
B24: 2022 | C24: 20 | D24: 14654 | E24: =365 - IF(C22<=5,8,IF(C22<=10,12,16)) -> 349 | F24: =F23*(1+0.03)*(1+0.01) -> 8473.7054 | G24: =F24*365 -> 3092902.5
B25: 2023 | C25: 21 | D25: 14823 | E25: =365 - IF(C23<=5,8,IF(C23<=10,12,16)) -> 349 | F25: =F24*(1+0.03)*(1+0.01) -> 8815.1958 | G25: =F25*365 -> 3217546.5
B26: 2024 | C26: 22 | D26: 14993 | E26: 350 | F26: =F25*(1+0.03)*(1+0.01) -> 9170.4481 | G26: =F26*366 -> 3356384 | H26: leap year
B27: 2025 | C27: 23 | D27: 15166 | E27: =365 - IF(C25<=5,8,IF(C25<=10,12,16)) -> 349 | F27: =F26*(1+0.03)*(1+0.01) -> 9540.0172 | G27: =F27*365 -> 3482106.3
B28: 2026 | C28: 24 | D28: 15341 | E28: =365 - IF(C26<=5,8,IF(C26<=10,12,16)) -> 349 | F28: =F27*(1+0.03)*(1+0.01) -> 9924.4799 | G28: =F28*365 -> 3622435.2
B29: 2027 | C29: 25 | D29: 13448 | E29: =365 - IF(C27<=5,8,IF(C27<=10,12,16)) -> 349 | F29: =F28*(1+0.03)*(1+0.01) -> 10324.436 | G29: =F29*365 -> 3768419.3
F31: Increase by 4.03% each year

Sheet Cash flows
C2: Year | D2: Age (yrs) | E2: Revenues | F2: Operatig Expenses | G2: Depreciation | H2: EBIT | I2: Tax (NY) | J2: Tax (HK) | K2: Net Income NY | L2: OCF NY | M2: OCF HK | N2: Capex | O2: ΔNWC | P2: FCF (NY) | Q2: FCF (HK) | R2: DCF (NY) | S2: DCF (HK) | T2: Period | W2: NPV NY | X2: =SUM(R3:R29) -> -4848076.6 | Y2: IRR | Z2: =IRR(P3:P29) -> 0.066435262
C3: 2001 | N3: -3900000 | P3: -3900000 | Q3: -3900000 | R3: =P3/(1.09)^$T3 -> -3900000 | S3: =Q3/1.09^$T3 -> -3900000 | T3: 0 | W3: NPV HK | X3: =SUM(S3:S29) -> 3467958.4 | Y3: IRR | Z3: =IRR(Q3:Q29) -> 0.10752725
C4: 2002 | N4: -3900000 | P4: -3900000 | Q4: -3900000 | R4: =P4/(1.09)^$T4 -> -3577981.7 | S4: =Q4/1.09^$T4 -> -3577981.7 | T4: 1
C5: 2003 | D5: 1 | E5: ='Rates & Ops'!D5*'Rates & Ops'!E5 -> 7140000 | F5: ='Rates & Ops'!G5 -> 1460000 | G5: =39000000/25 -> 1560000 | H5: =E5-F5-G5 -> 4120000 | I5: =MAX(0, H5 * Inputs!$C$19) -> 1442000 | J5: 0 | K5: =0.65*Table1[[#This Row],[EBIT]] -> 2678000 | L5: =H5*0.65+G5 -> 4238000 | M5: =H5+G5 -> 5680000 | N5: -31200000 | O5: -500000 | P5: =L5+N5+O5 -> -27462000 | Q5: =M5+N5+O5 -> -26020000 | R5: =P5/(1.09)^$T5 -> -23114216 | S5: =Q5/1.09^$T5 -> -21900513 | T5: 2 | U5: 500000
C6: 2004 | D6: 2 | E6: ='Rates & Ops'!D6*'Rates & Ops'!E6 -> 7231600 | F6: ='Rates & Ops'!G6 -> 1522999.2 | G6: =39000000/25 -> 1560000 | H6: =E6-F6-G6 -> 4148600.8 | I6: =MAX(0, H6 * Inputs!$C$19) -> 1452010.3 | J6: 0 | K6: =0.65*Table1[[#This Row],[EBIT]] -> 2696590.5 | L6: =H6*0.65+G6 -> 4256590.5 | M6: =H6+G6 -> 5708600.8 | O6: =-(U6-U5) -> -15000 | P6: =L6+N6+O6 -> 4241590.5 | Q6: =M6+N6+O6 -> 5693600.8 | R6: =P6/(1.09)^$T6 -> 3275286.1 | S6: =Q6/1.09^$T6 -> 4396504.5 | T6: 3 | U6: =U5*1.03 -> 515000
C7: 2005 | D7: 3 | E7: ='Rates & Ops'!D7*'Rates & Ops'!E7 -> 7282800 | F7: ='Rates & Ops'!G7 -> 1580047.2 | G7: =39000000/25 -> 1560000 | H7: =E7-F7-G7 -> 4142752.8 | I7: =MAX(0, H7 * Inputs!$C$19) -> 1449963.5 | J7: 0 | K7: =0.65*Table1[[#This Row],[EBIT]] -> 2692789.3 | L7: =H7*0.65+G7 -> 4252789.3 | M7: =H7+G7 -> 5702752.8 | O7: =-(U7-U6) -> -15450 | P7: =L7+N7+O7 -> 4237339.3 | Q7: =M7+N7+O7 -> 5687302.8 | R7: =P7/(1.09)^$T7 -> 3001838 | S7: =Q7/1.09^$T7 -> 4029028.7 | T7: 4 | U7: =U6*1.03 -> 530450
C8: 2006 | D8: 4 | E8: ='Rates & Ops'!D8*'Rates & Ops'!E8 -> 6680898 | F8: ='Rates & Ops'!G8 -> 1643723.1 | G8: =39000000/25 -> 1560000 | H8: =E8-F8-G8 -> 3477174.9 | I8: =MAX(0, H8 * Inputs!$C$19) -> 1217011.2 | J8: 0 | K8: =0.65*Table1[[#This Row],[EBIT]] -> 2260163.7 | L8: =H8*0.65+G8 -> 3820163.7 | M8: =H8+G8 -> 5037174.9 | O8: =-(U8-U7) -> -15913.5 | P8: =L8+N8+O8 -> 3804250.2 | Q8: =M8+N8+O8 -> 5021261.4 | R8: =P8/(1.09)^$T8 -> 2472501.6 | S8: =Q8/1.09^$T8 -> 3263475.4 | T8: 5 | U8: =U7*1.03 -> 546363.5
C9: 2007 | D9: 5 | E9: ='Rates & Ops'!D9*'Rates & Ops'!E9 -> 6170031 | F9: ='Rates & Ops'!G9 -> 1709965.1 | G9: =39000000/25 -> 1560000 | H9: =E9-F9-G9 -> 2900065.9 | I9: =MAX(0, H9 * Inputs!$C$19) -> 1015023.1 | J9: 0 | K9: =0.65*Table1[[#This Row],[EBIT]] -> 1885042.8 | L9: =H9*0.65+G9 -> 3445042.8 | M9: =H9+G9 -> 4460065.9 | N9: -300000 | O9: =-(U9-U8) -> -16390.905 | P9: =L9+N9+O9 -> 3128651.9 | Q9: =M9+N9+O9 -> 4143675 | R9: =P9/(1.09)^$T9 -> 1865512.9 | S9: =Q9/1.09^$T9 -> 2470738 | T9: 6 | U9: =U8*1.03 -> 562754.41
C10: 2008 | D10: 6 | E10: ='Rates & Ops'!D10*'Rates & Ops'!E10 -> 6188274 | F10: ='Rates & Ops'!G10 -> 1783750.3 | G10: =39000000/25+300000/5 -> 1620000 | H10: =E10-F10-G10 -> 2784523.7 | I10: =MAX(0, H10 * Inputs!$C$19) -> 974583.28 | J10: 0 | K10: =0.65*Table1[[#This Row],[EBIT]] -> 1809940.4 | L10: =H10*0.65+G10 -> 3429940.4 | M10: =H10+G10 -> 4404523.7 | N10: 0 | O10: =-(U10-U9) -> -16882.632 | P10: =L10+N10+O10 -> 3413057.7 | Q10: =M10+N10+O10 -> 4387641 | R10: =P10/(1.09)^$T10 -> 1867059.5 | S10: =Q10/1.09^$T10 -> 2400189.9 | T10: 7 | U10: =U9*1.03 -> 579637.04
C11: 2009 | D11: 7 | E11: ='Rates & Ops'!D11*'Rates & Ops'!E11 -> 6241746 | F11: ='Rates & Ops'!G11 -> 1850565.4 | G11: =39000000/25+300000/5 -> 1620000 | H11: =E11-F11-G11 -> 2771180.6 | I11: =MAX(0, H11 * Inputs!$C$19) -> 969913.2 | J11: 0 | K11: =0.65*Table1[[#This Row],[EBIT]] -> 1801267.4 | L11: =H11*0.65+G11 -> 3421267.4 | M11: =H11+G11 -> 4391180.6 | N11: 0 | O11: =-(U11-U10) -> -17389.111 | P11: =L11+N11+O11 -> 3403878.3 | Q11: =M11+N11+O11 -> 4373791.5 | R11: =P11/(1.09)^$T11 -> 1708291.7 | S11: =Q11/1.09^$T11 -> 2195058.4 | T11: 8 | U11: =U10*1.03 -> 597026.15
C12: 2010 | D12: 8 | E12: ='Rates & Ops'!D12*'Rates & Ops'!E12 -> 6313758 | F12: ='Rates & Ops'!G12 -> 1925143.2 | G12: =39000000/25+300000/5 -> 1620000 | H12: =E12-F12-G12 -> 2768614.8 | I12: =MAX(0, H12 * Inputs!$C$19) -> 969015.17 | J12: 0 | K12: =0.65*Table1[[#This Row],[EBIT]] -> 1799599.6 | L12: =H12*0.65+G12 -> 3419599.6 | M12: =H12+G12 -> 4388614.8 | N12: 0 | O12: =-(U12-U11) -> -17910.784 | P12: =L12+N12+O12 -> 3401688.8 | Q12: =M12+N12+O12 -> 4370704 | R12: =P12/(1.09)^$T12 -> 1566232 | S12: =Q12/1.09^$T12 -> 2012393.5 | T12: 9 | U12: =U11*1.03 -> 614936.93
C13: 2011 | D13: 9 | E13: ='Rates & Ops'!D13*'Rates & Ops'!E13 -> 6386476 | F13: ='Rates & Ops'!G13 -> 2002726.5 | G13: =39000000/25+300000/5 -> 1620000 | H13: =E13-F13-G13 -> 2763749.5 | I13: =MAX(0, H13 * Inputs!$C$19) -> 967312.33 | J13: 0 | K13: =0.65*Table1[[#This Row],[EBIT]] -> 1796437.2 | L13: =H13*0.65+G13 -> 3416437.2 | M13: =H13+G13 -> 4383749.5 | N13: 0 | O13: =-(U13-U12) -> -18448.108 | P13: =L13+N13+O13 -> 3397989.1 | Q13: =M13+N13+O13 -> 4365301.4 | R13: =P13/(1.09)^$T13 -> 1435347.3 | S13: =Q13/1.09^$T13 -> 1843950.5 | T13: 10 | U13: =U12*1.03 -> 633385.04
C14: 2012 | D14: 10 | E14: ='Rates & Ops'!D14*'Rates & Ops'!E14 -> 6169512 | F14: ='Rates & Ops'!G14 -> 2089144.4 | G14: =39000000/25+300000/5 -> 1620000 | H14: =E14-F14-G14 -> 2460367.6 | I14: =MAX(0, H14 * Inputs!$C$19) -> 861128.65 | J14: 0 | K14: =0.65*Table1[[#This Row],[EBIT]] -> 1599238.9 | L14: =H14*0.65+G14 -> 3219238.9 | M14: =H14+G14 -> 4080367.6 | N14: -350000 | O14: =-(U14-U13) -> -19001.551 | P14: =L14+N14+O14 -> 2850237.4 | Q14: =M14+N14+O14 -> 3711366 | R14: =P14/(1.09)^$T14 -> 1104560.6 | S14: =Q14/1.09^$T14 -> 1438276.3 | T14: 11 | U14: =U13*1.03 -> 652386.59
C15: 2013 | D15: 11 | E15: ='Rates & Ops'!D15*'Rates & Ops'!E15 -> 6152172 | F15: ='Rates & Ops'!G15 -> 2167398.9 | G15: =39000000/25+350000/5 -> 1630000 | H15: =E15-F15-G15 -> 2354773.1 | I15: =MAX(0, H15 * Inputs!$C$19) -> 824170.6 | J15: 0 | K15: =0.65*Table1[[#This Row],[EBIT]] -> 1530602.5 | L15: =H15*0.65+G15 -> 3160602.5 | M15: =H15+G15 -> 3984773.1 | N15: 0 | O15: =-(U15-U14) -> -19571.598 | P15: =L15+N15+O15 -> 3141030.9 | Q15: =M15+N15+O15 -> 3965201.5 | R15: =P15/(1.09)^$T15 -> 1116745.6 | S15: =Q15/1.09^$T15 -> 1409766.8 | T15: 12 | U15: =U14*1.03 -> 671958.19
C16: 2014 | D16: 12 | E16: ='Rates & Ops'!D16*'Rates & Ops'!E16 -> 6223019 | F16: ='Rates & Ops'!G16 -> 2254745 | G16: =39000000/25+350000/5 -> 1630000 | H16: =E16-F16-G16 -> 2338274 | I16: =MAX(0, H16 * Inputs!$C$19) -> 818395.89 | J16: 0 | K16: =0.65*Table1[[#This Row],[EBIT]] -> 1519878.1 | L16: =H16*0.65+G16 -> 3149878.1 | M16: =H16+G16 -> 3968274 | N16: 0 | O16: =-(U16-U15) -> -20158.746 | P16: =L16+N16+O16 -> 3129719.3 | Q16: =M16+N16+O16 -> 3948115.2 | R16: =P16/(1.09)^$T16 -> 1020847.6 | S16: =Q16/1.09^$T16 -> 1287790.9 | T16: 13 | U16: =U15*1.03 -> 692116.94
C17: 2015 | D17: 13 | E17: ='Rates & Ops'!D17*'Rates & Ops'!E17 -> 6294564 | F17: ='Rates & Ops'!G17 -> 2345611.3 | G17: =39000000/25+350000/5 -> 1630000 | H17: =E17-F17-G17 -> 2318952.7 | I17: =MAX(0, H17 * Inputs!$C$19) -> 811633.46 | J17: 0 | K17: =0.65*Table1[[#This Row],[EBIT]] -> 1507319.3 | L17: =H17*0.65+G17 -> 3137319.3 | M17: =H17+G17 -> 3948952.7 | N17: 0 | O17: =-(U17-U16) -> -20763.508 | P17: =L17+N17+O17 -> 3116555.8 | Q17: =M17+N17+O17 -> 3928189.2 | R17: =P17/(1.09)^$T17 -> 932618.3 | S17: =Q17/1.09^$T17 -> 1175496.7 | T17: 14 | U17: =U16*1.03 -> 712880.44
C18: 2016 | D18: 14 | E18: ='Rates & Ops'!D18*'Rates & Ops'!E18 -> 6385050 | F18: ='Rates & Ops'!G18 -> 2446824.7 | G18: =39000000/25+350000/5 -> 1630000 | H18: =E18-F18-G18 -> 2308225.3 | I18: =MAX(0, H18 * Inputs!$C$19) -> 807878.85 | J18: 0 | K18: =0.65*Table1[[#This Row],[EBIT]] -> 1500346.4 | L18: =H18*0.65+G18 -> 3130346.4 | M18: =H18+G18 -> 3938225.3 | N18: 0 | O18: =-(U18-U17) -> -21386.413 | P18: =L18+N18+O18 -> 3108960 | Q18: =M18+N18+O18 -> 3916838.9 | R18: =P18/(1.09)^$T18 -> 853527.8 | S18: =Q18/1.09^$T18 -> 1075321.3 | T18: 15 | U18: =U17*1.03 -> 734266.86
C19: 2017 | D19: 15 | E19: ='Rates & Ops'!D19*'Rates & Ops'!E19 -> 5151938 | F19: ='Rates & Ops'!G19 -> 2538477 | G19: =39000000/25+350000/5 -> 1630000 | H19: =E19-F19-G19 -> 983460.99 | I19: =MAX(0, H19 * Inputs!$C$19) -> 344211.35 | J19: 0 | K19: =0.65*Table1[[#This Row],[EBIT]] -> 639249.64 | L19: =H19*0.65+G19 -> 2269249.6 | M19: =H19+G19 -> 2613461 | N19: -750000 | O19: =-(U19-U18) -> -22028.006 | P19: =L19+N19+O19 -> 1497221.6 | Q19: =M19+N19+O19 -> 1841433 | R19: =P19/(1.09)^$T19 -> 377104.86 | S19: =Q19/1.09^$T19 -> 463801.29 | T19: 16 | U19: =U18*1.03 -> 756294.86
C20: 2018 | D20: 16 | E20: ='Rates & Ops'!D20*'Rates & Ops'!E20 -> 5211268 | F20: ='Rates & Ops'!G20 -> 2640777.6 | G20: =39000000/25+750000/5 -> 1710000 | H20: =E20-F20-G20 -> 860490.37 | I20: =MAX(0, H20 * Inputs!$C$19) -> 301171.63 | J20: 0 | K20: =0.65*Table1[[#This Row],[EBIT]] -> 559318.74 | L20: =H20*0.65+G20 -> 2269318.7 | M20: =H20+G20 -> 2570490.4 | N20: 0 | O20: =-(U20-U19) -> -22688.846 | P20: =L20+N20+O20 -> 2246629.9 | Q20: =M20+N20+O20 -> 2547801.5 | R20: =P20/(1.09)^$T20 -> 519135.91 | S20: =Q20/1.09^$T20 -> 588728.59 | T20: 17 | U20: =U19*1.03 -> 778983.71
C21: 2019 | D21: 17 | E21: ='Rates & Ops'!D21*'Rates & Ops'!E21 -> 5271296 | F21: ='Rates & Ops'!G21 -> 2747201 | G21: =39000000/25+750000/5 -> 1710000 | H21: =E21-F21-G21 -> 814095.03 | I21: =MAX(0, H21 * Inputs!$C$19) -> 284933.26 | J21: 0 | K21: =0.65*Table1[[#This Row],[EBIT]] -> 529161.77 | L21: =H21*0.65+G21 -> 2239161.8 | M21: =H21+G21 -> 2524095 | N21: 0 | O21: =-(U21-U20) -> -23369.511 | P21: =L21+N21+O21 -> 2215792.3 | Q21: =M21+N21+O21 -> 2500725.5 | R21: =P21/(1.09)^$T21 -> 469734.09 | S21: =Q21/1.09^$T21 -> 530138.16 | T21: 18 | U21: =U20*1.03 -> 802353.22
C22: 2020 | D22: 18 | E22: ='Rates & Ops'!D22*'Rates & Ops'!E22 -> 5347300 | F22: ='Rates & Ops'!G22 -> 2865743.1 | G22: =39000000/25+750000/5 -> 1710000 | H22: =E22-F22-G22 -> 771556.93 | I22: =MAX(0, H22 * Inputs!$C$19) -> 270044.93 | J22: 0 | K22: =0.65*Table1[[#This Row],[EBIT]] -> 501512 | L22: =H22*0.65+G22 -> 2211512 | M22: =H22+G22 -> 2481556.9 | N22: 0 | O22: =-(U22-U21) -> -24070.597 | P22: =L22+N22+O22 -> 2187441.4 | Q22: =M22+N22+O22 -> 2457486.3 | R22: =P22/(1.09)^$T22 -> 425434.76 | S22: =Q22/1.09^$T22 -> 477955.71 | T22: 19 | U22: =U21*1.03 -> 826423.82
C23: 2021 | D23: 19 | E23: ='Rates & Ops'!D23*'Rates & Ops'!E23 -> 5393446 | F23: ='Rates & Ops'!G23 -> 2973087.1 | G23: =39000000/25+750000/5 -> 1710000 | H23: =E23-F23-G23 -> 710358.93 | I23: =MAX(0, H23 * Inputs!$C$19) -> 248625.62 | J23: 0 | K23: =0.65*Table1[[#This Row],[EBIT]] -> 461733.3 | L23: =H23*0.65+G23 -> 2171733.3 | M23: =H23+G23 -> 2420358.9 | N23: 0 | O23: =-(U23-U22) -> -24792.714 | P23: =L23+N23+O23 -> 2146940.6 | Q23: =M23+N23+O23 -> 2395566.2 | R23: =P23/(1.09)^$T23 -> 383080.52 | S23: =Q23/1.09^$T23 -> 427443.01 | T23: 20 | U23: =U22*1.03 -> 851216.53
C24: 2022 | D24: 20 | E24: ='Rates & Ops'!D24*'Rates & Ops'!E24 -> 5114246 | F24: ='Rates & Ops'!G24 -> 3092902.5 | G24: =39000000/25+750000/5 -> 1710000 | H24: =E24-F24-G24 -> 311343.52 | I24: =MAX(0, H24 * Inputs!$C$19) -> 108970.23 | J24: 0 | K24: =0.65*Table1[[#This Row],[EBIT]] -> 202373.29 | L24: =H24*0.65+G24 -> 1912373.3 | M24: =H24+G24 -> 2021343.5 | N24: -850000 | O24: =-(U24-U23) -> -25536.496 | P24: =L24+N24+O24 -> 1036836.8 | Q24: =M24+N24+O24 -> 1145807 | R24: =P24/(1.09)^$T24 -> 169728.18 | S24: =Q24/1.09^$T24 -> 187566.39 | T24: 21 | U24: =U23*1.03 -> 876753.03
C25: 2023 | D25: 21 | E25: ='Rates & Ops'!D25*'Rates & Ops'!E25 -> 5173227 | F25: ='Rates & Ops'!G25 -> 3217546.5 | G25: =39000000/25+850000/5 -> 1730000 | H25: =E25-F25-G25 -> 225680.55 | I25: =MAX(0, H25 * Inputs!$C$19) -> 78988.192 | J25: 0 | K25: =0.65*Table1[[#This Row],[EBIT]] -> 146692.36 | L25: =H25*0.65+G25 -> 1876692.4 | M25: =H25+G25 -> 1955680.5 | N25: 0 | O25: =-(U25-U24) -> -26302.591 | P25: =L25+N25+O25 -> 1850389.8 | Q25: =M25+N25+O25 -> 1929378 | R25: =P25/(1.09)^$T25 -> 277894.7 | S25: =Q25/1.09^$T25 -> 289757.28 | T25: 22 | U25: =U24*1.03 -> 903055.62
C26: 2024 | D26: 22 | E26: ='Rates & Ops'!D26*'Rates & Ops'!E26 -> 5247550 | F26: ='Rates & Ops'!G26 -> 3356384 | G26: =39000000/25+850000/5 -> 1730000 | H26: =E26-F26-G26 -> 161165.98 | I26: =MAX(0, H26 * Inputs!$C$19) -> 56408.092 | J26: 0 | K26: =0.65*Table1[[#This Row],[EBIT]] -> 104757.89 | L26: =H26*0.65+G26 -> 1834757.9 | M26: =H26+G26 -> 1891166 | N26: 0 | O26: =-(U26-U25) -> -27091.669 | P26: =L26+N26+O26 -> 1807666.2 | Q26: =M26+N26+O26 -> 1864074.3 | R26: =P26/(1.09)^$T26 -> 249062.76 | S26: =Q26/1.09^$T26 -> 256834.74 | T26: 23 | U26: =U25*1.03 -> 930147.29
C27: 2025 | D27: 23 | E27: ='Rates & Ops'!D27*'Rates & Ops'!E27 -> 5292934 | F27: ='Rates & Ops'!G27 -> 3482106.3 | G27: =39000000/25+850000/5 -> 1730000 | H27: =E27-F27-G27 -> 80827.719 | I27: =MAX(0, H27 * Inputs!$C$19) -> 28289.702 | J27: 0 | K27: =0.65*Table1[[#This Row],[EBIT]] -> 52538.017 | L27: =H27*0.65+G27 -> 1782538 | M27: =H27+G27 -> 1810827.7 | N27: 0 | O27: =-(U27-U26) -> -27904.419 | P27: =L27+N27+O27 -> 1754633.6 | Q27: =M27+N27+O27 -> 1782923.3 | R27: =P27/(1.09)^$T27 -> 221794.36 | S27: =Q27/1.09^$T27 -> 225370.31 | T27: 24 | U27: =U26*1.03 -> 958051.7
C28: 2026 | D28: 24 | E28: ='Rates & Ops'!D28*'Rates & Ops'!E28 -> 5354009 | F28: ='Rates & Ops'!G28 -> 3622435.2 | G28: =39000000/25+850000/5 -> 1730000 | H28: =E28-F28-G28 -> 1573.8361 | I28: =MAX(0, H28 * Inputs!$C$19) -> 550.84262 | J28: 0 | K28: =0.65*Table1[[#This Row],[EBIT]] -> 1022.9934 | L28: =H28*0.65+G28 -> 1731023 | M28: =H28+G28 -> 1731573.8 | N28: 0 | O28: =-(U28-U27) -> -28741.551 | P28: =L28+N28+O28 -> 1702281.4 | Q28: =M28+N28+O28 -> 1702832.3 | R28: =P28/(1.09)^$T28 -> 197409.89 | S28: =Q28/1.09^$T28 -> 197473.77 | T28: 25 | U28: =U27*1.03 -> 986793.26
C29: 2027 | D29: 25 | E29: ='Rates & Ops'!D29*'Rates & Ops'!E29 -> 4693352 | F29: ='Rates & Ops'!G29 -> 3768419.3 | G29: =39000000/25+850000/5 -> 1730000 | H29: =E29-F29-G29 -> -805067.3 | I29: =MAX(0, H29 * Inputs!$C$19) -> 0 | J29: 0 | K29: =0.65*Table1[[#This Row],[EBIT]] -> -523293.75 | L29: =H29*0.65+G29 -> 1206706.3 | M29: =H29+G29 -> 924932.7 | N29: 0 | O29: 986793.26 | P29: =L29+N29+O29 -> 2193499.5 | Q29: =M29+N29+O29 -> 1911726 | R29: =P29/(1.09)^$T29 -> 233371.92 | S29: =Q29/1.09^$T29 -> 203393.32 | T29: 26 | U29: =U28*1.03 -> 1016397.1
U30: =U29*1.03 -> 1046889
U31: =U30*1.03 -> 1078295.6
K36: 4
C40: Year | D40: Age (yrs) | E40: Revenue | F40: Op Cost | G40: Depreciation | H40: EBIT | I40: Tax (NY) | J40: Tax (HK) | K40: Net Income NY | L40: OCF NY | M40: OCF HK | N40: Capex | O40: ΔNWC | P40: FCF (NY) | Q40: FCF (HK) | R40: DCF (NY) | S40: DCF (HK) | T40: Period
C41: 2001 | N41: -3900000 | P41: -3900000 | Q41: -3900000 | R41: =P41/1.09^$T41 -> -3900000 | S41: =Q41/((1.09)^$T41) -> -3900000 | T41: 0 | W41: NPV NY | X41: =SUM(R41:R57) -> -5421547.9 | Y41: IRR | Z41: =IRR(P41:P57) -> 0.060353915
C42: 2002 | N42: -3900000 | P42: -3900000 | Q42: -3900000 | R42: =P42/1.09^$T42 -> -3577981.7 | S42: =Q42/(1.09^$T42) -> -3577981.7 | T42: 1 | W42: NPV HK | X42: =SUM(S41:S57) -> 1722036.1 | Y42: IRR | Z42: =IRR(Q41:Q57) -> 0.099967097
C43: 2003 | D43: 1 | E43: ='Rates & Ops'!D5*'Rates & Ops'!E5 -> 7140000 | F43: ='Rates & Ops'!G5 -> 1460000 | G43: 1560000 | H43: =E43-F43-G43 -> 4120000 | I43: =MAX(0, H43 * Inputs!$C$19) -> 1442000 | J43: 0 | K43: =0.65*Table2[[#This Row],[EBIT]] -> 2678000 | L43: =H43*0.65+G43 -> 4238000 | M43: =H43+G43 -> 5680000 | N43: -31200000 | O43: -500000 | P43: =L43+N43+O43 -> -27462000 | Q43: =M43+N43+O43 -> -26020000 | R43: =P43/1.09^$T43 -> -23114216 | S43: =Q43/1.09^$T43 -> -21900513 | T43: 2
C44: 2004 | D44: 2 | E44: ='Rates & Ops'!D6*'Rates & Ops'!E6 -> 7231600 | F44: ='Rates & Ops'!G6 -> 1522999.2 | G44: 1560000 | H44: =E44-F44-G44 -> 4148600.8 | I44: =MAX(0, H44 * Inputs!$C$19) -> 1452010.3 | J44: 0 | K44: =0.65*Table2[[#This Row],[EBIT]] -> 2696590.5 | L44: =H44*0.65+G44 -> 4256590.5 | M44: =H44+G44 -> 5708600.8 | O44: -15000 | P44: =L44+N44+O44 -> 4241590.5 | Q44: =M44+N44+O44 -> 5693600.8 | R44: =P44/1.09^$T44 -> 3275286.1 | S44: =Q44/1.09^$T44 -> 4396504.5 | T44: 3
C45: 2005 | D45: 3 | E45: ='Rates & Ops'!D7*'Rates & Ops'!E7 -> 7282800 | F45: ='Rates & Ops'!G7 -> 1580047.2 | G45: 1560000 | H45: =E45-F45-G45 -> 4142752.8 | I45: =MAX(0, H45 * Inputs!$C$19) -> 1449963.5 | J45: 0 | K45: =0.65*Table2[[#This Row],[EBIT]] -> 2692789.3 | L45: =H45*0.65+G45 -> 4252789.3 | M45: =H45+G45 -> 5702752.8 | O45: -15450 | P45: =L45+N45+O45 -> 4237339.3 | Q45: =M45+N45+O45 -> 5687302.8 | R45: =P45/1.09^$T45 -> 3001838 | S45: =Q45/1.09^$T45 -> 4029028.7 | T45: 4
C46: 2006 | D46: 4 | E46: ='Rates & Ops'!D8*'Rates & Ops'!E8 -> 6680898 | F46: ='Rates & Ops'!G8 -> 1643723.1 | G46: 1560000 | H46: =E46-F46-G46 -> 3477174.9 | I46: =MAX(0, H46 * Inputs!$C$19) -> 1217011.2 | J46: 0 | K46: =0.65*Table2[[#This Row],[EBIT]] -> 2260163.7 | L46: =H46*0.65+G46 -> 3820163.7 | M46: =H46+G46 -> 5037174.9 | O46: -15913.5 | P46: =L46+N46+O46 -> 3804250.2 | Q46: =M46+N46+O46 -> 5021261.4 | R46: =P46/1.09^$T46 -> 2472501.6 | S46: =Q46/1.09^$T46 -> 3263475.4 | T46: 5
C47: 2007 | D47: 5 | E47: ='Rates & Ops'!D9*'Rates & Ops'!E9 -> 6170031 | F47: ='Rates & Ops'!G9 -> 1709965.1 | G47: 1560000 | H47: =E47-F47-G47 -> 2900065.9 | I47: =MAX(0, H47 * Inputs!$C$19) -> 1015023.1 | J47: 0 | K47: =0.65*Table2[[#This Row],[EBIT]] -> 1885042.8 | L47: =H47*0.65+G47 -> 3445042.8 | M47: =H47+G47 -> 4460065.9 | N47: -300000 | O47: -16390.905 | P47: =L47+N47+O47 -> 3128651.9 | Q47: =M47+N47+O47 -> 4143675 | R47: =P47/1.09^$T47 -> 1865512.9 | S47: =Q47/1.09^$T47 -> 2470738 | T47: 6
C48: 2008 | D48: 6 | E48: ='Rates & Ops'!D10*'Rates & Ops'!E10 -> 6188274 | F48: ='Rates & Ops'!G10 -> 1783750.3 | G48: 1620000 | H48: =E48-F48-G48 -> 2784523.7 | I48: =MAX(0, H48 * Inputs!$C$19) -> 974583.28 | J48: 0 | K48: =0.65*Table2[[#This Row],[EBIT]] -> 1809940.4 | L48: =H48*0.65+G48 -> 3429940.4 | M48: =H48+G48 -> 4404523.7 | N48: 0 | O48: -16882.632 | P48: =L48+N48+O48 -> 3413057.7 | Q48: =M48+N48+O48 -> 4387641 | R48: =P48/1.09^$T48 -> 1867059.5 | S48: =Q48/1.09^$T48 -> 2400189.9 | T48: 7
C49: 2009 | D49: 7 | E49: ='Rates & Ops'!D11*'Rates & Ops'!E11 -> 6241746 | F49: ='Rates & Ops'!G11 -> 1850565.4 | G49: 1620000 | H49: =E49-F49-G49 -> 2771180.6 | I49: =MAX(0, H49 * Inputs!$C$19) -> 969913.2 | J49: 0 | K49: =0.65*Table2[[#This Row],[EBIT]] -> 1801267.4 | L49: =H49*0.65+G49 -> 3421267.4 | M49: =H49+G49 -> 4391180.6 | N49: 0 | O49: -17389.111 | P49: =L49+N49+O49 -> 3403878.3 | Q49: =M49+N49+O49 -> 4373791.5 | R49: =P49/1.09^$T49 -> 1708291.7 | S49: =Q49/1.09^$T49 -> 2195058.4 | T49: 8
C50: 2010 | D50: 8 | E50: ='Rates & Ops'!D12*'Rates & Ops'!E12 -> 6313758 | F50: ='Rates & Ops'!G12 -> 1925143.2 | G50: 1620000 | H50: =E50-F50-G50 -> 2768614.8 | I50: =MAX(0, H50 * Inputs!$C$19) -> 969015.17 | J50: 0 | K50: =0.65*Table2[[#This Row],[EBIT]] -> 1799599.6 | L50: =H50*0.65+G50 -> 3419599.6 | M50: =H50+G50 -> 4388614.8 | N50: 0 | O50: -17910.784 | P50: =L50+N50+O50 -> 3401688.8 | Q50: =M50+N50+O50 -> 4370704 | R50: =P50/1.09^$T50 -> 1566232 | S50: =Q50/1.09^$T50 -> 2012393.5 | T50: 9
C51: 2011 | D51: 9 | E51: ='Rates & Ops'!D13*'Rates & Ops'!E13 -> 6386476 | F51: ='Rates & Ops'!G13 -> 2002726.5 | G51: 1620000 | H51: =E51-F51-G51 -> 2763749.5 | I51: =MAX(0, H51 * Inputs!$C$19) -> 967312.33 | J51: 0 | K51: =0.65*Table2[[#This Row],[EBIT]] -> 1796437.2 | L51: =H51*0.65+G51 -> 3416437.2 | M51: =H51+G51 -> 4383749.5 | N51: 0 | O51: -18448.108 | P51: =L51+N51+O51 -> 3397989.1 | Q51: =M51+N51+O51 -> 4365301.4 | R51: =P51/1.09^$T51 -> 1435347.3 | S51: =Q51/1.09^$T51 -> 1843950.5 | T51: 10
C52: 2012 | D52: 10 | E52: ='Rates & Ops'!D14*'Rates & Ops'!E14 -> 6169512 | F52: ='Rates & Ops'!G14 -> 2089144.4 | G52: 1620000 | H52: =E52-F52-G52 -> 2460367.6 | I52: =MAX(0, H52 * Inputs!$C$19) -> 861128.65 | J52: 0 | K52: =0.65*Table2[[#This Row],[EBIT]] -> 1599238.9 | L52: =H52*0.65+G52 -> 3219238.9 | M52: =H52+G52 -> 4080367.6 | N52: -350000 | O52: -19001.551 | P52: =L52+N52+O52 -> 2850237.4 | Q52: =M52+N52+O52 -> 3711366 | R52: =P52/1.09^$T52 -> 1104560.6 | S52: =Q52/1.09^$T52 -> 1438276.3 | T52: 11
C53: 2013 | D53: 11 | E53: ='Rates & Ops'!D15*'Rates & Ops'!E15 -> 6152172 | F53: ='Rates & Ops'!G15 -> 2167398.9 | G53: 1630000 | H53: =E53-F53-G53 -> 2354773.1 | I53: =MAX(0, H53 * Inputs!$C$19) -> 824170.6 | J53: 0 | K53: =0.65*Table2[[#This Row],[EBIT]] -> 1530602.5 | L53: =H53*0.65+G53 -> 3160602.5 | M53: =H53+G53 -> 3984773.1 | N53: 0 | O53: -19571.598 | P53: =L53+N53+O53 -> 3141030.9 | Q53: =M53+N53+O53 -> 3965201.5 | R53: =P53/1.09^$T53 -> 1116745.6 | S53: =Q53/1.09^$T53 -> 1409766.8 | T53: 12
C54: 2014 | D54: 12 | E54: ='Rates & Ops'!D16*'Rates & Ops'!E16 -> 6223019 | F54: ='Rates & Ops'!G16 -> 2254745 | G54: 1630000 | H54: =E54-F54-G54 -> 2338274 | I54: =MAX(0, H54 * Inputs!$C$19) -> 818395.89 | J54: 0 | K54: =0.65*Table2[[#This Row],[EBIT]] -> 1519878.1 | L54: =H54*0.65+G54 -> 3149878.1 | M54: =H54+G54 -> 3968274 | N54: 0 | O54: -20158.746 | P54: =L54+N54+O54 -> 3129719.3 | Q54: =M54+N54+O54 -> 3948115.2 | R54: =P54/1.09^$T54 -> 1020847.6 | S54: =Q54/1.09^$T54 -> 1287790.9 | T54: 13
C55: 2015 | D55: 13 | E55: ='Rates & Ops'!D17*'Rates & Ops'!E17 -> 6294564 | F55: ='Rates & Ops'!G17 -> 2345611.3 | G55: 1630000 | H55: =E55-F55-G55 -> 2318952.7 | I55: =MAX(0, H55 * Inputs!$C$19) -> 811633.46 | J55: 0 | K55: =0.65*Table2[[#This Row],[EBIT]] -> 1507319.3 | L55: =H55*0.65+G55 -> 3137319.3 | M55: =H55+G55 -> 3948952.7 | N55: 0 | O55: -20763.508 | P55: =L55+N55+O55 -> 3116555.8 | Q55: =M55+N55+O55 -> 3928189.2 | R55: =P55/1.09^$T55 -> 932618.3 | S55: =Q55/1.09^$T55 -> 1175496.7 | T55: 14
C56: 2016 | D56: 14 | E56: ='Rates & Ops'!D18*'Rates & Ops'!E18 -> 6385050 | F56: ='Rates & Ops'!G18 -> 2446824.7 | G56: 1630000 | H56: =E56-F56-G56 -> 2308225.3 | I56: =MAX(0, H56 * Inputs!$C$19) -> 807878.85 | J56: 0 | K56: =0.65*Table2[[#This Row],[EBIT]] -> 1500346.4 | L56: =H56*0.65+G56 -> 3130346.4 | M56: =H56+G56 -> 3938225.3 | N56: 0 | O56: -21386.413 | P56: =L56+N56+O56 -> 3108960 | Q56: =M56+N56+O56 -> 3916838.9 | R56: =P56/1.09^$T56 -> 853527.8 | S56: =Q56/1.09^$T56 -> 1075321.3 | T56: 15
C57: 2017 | D57: 15 | E57: ='Rates & Ops'!D19*'Rates & Ops'!E19 -> 5151938 | F57: ='Rates & Ops'!G19 -> 2538477 | G57: =1560000+70000 -> 1630000 | H57: =E57-F57-G57 -> 983460.99 | I57: =MAX(0, H57 * Inputs!$C$19) -> 344211.35 | J57: 0 | K57: =0.65*Table2[[#This Row],[EBIT]] -> 639249.64 | L57: =H57*0.65+G57 -> 2269249.6 | M57: =H57+G57 -> 2613461 | N57: 5000000 | O57: =-SUM(O43:O56) -> 734266.86 | P57: =L57+N57+O57+3710000 -> 11713516 | Q57: =M57+N57+O57 -> 8347727.8 | R57: =P57/1.09^$T57 -> 2950280.6 | S57: =Q57/1.09^$T57 -> 2102540.2 | T57: 16
D62: 1) added 5 000 000 scrap value in the CF
E64: YOU DEPRECIATE in 2008 for the 2007 survey and …
F66: NPV of Investments (9% rate) | K66: IRR of Investments
F67: New York-based | H67: Hong Kong–based | K67: New York-based | M67: Hong Kong–based
F68: 15 years | G68: 25 years | H68: 15 years | I68: 25 years | K68: 15 years | L68: 25 years | M68: 15 years | N68: 25 years
F69: =SUM(Table2[DCF (NY)]) -> -5421547.9 | G69: =SUM(Table1[DCF (NY) ]) -> -4848076.6 | H69: =SUM(Table2[DCF (HK)]) -> 1722036.1 | I69: =SUM(Table1[DCF (HK)]) -> 3467958.4 | K69: =IRR(Table2[FCF (NY)]) -> 0.060353915 | L69: =IRR(Table1[FCF (NY)]) -> 0.066435262 | M69: =IRR(Table2[FCF (HK)]) -> 0.099967097 | N69: =IRR(Table1[FCF (HK)]) -> 0.10752725
D72: NPV HK 11% | E72: =SUM(E74:E100) -> -426617.45 | G72: NPV HK (15 Y) | H72: =SUM(F74:F90) -> -1540471.7
D74: DCF HK | E74: =Q3/1.11^$T3 -> -3900000 | F74: =Q41/1.11^$T41 -> -3900000 | K74: NPV of Investments (11% rate)
E75: =Q4/1.11^$T4 -> -3513513.5 | F75: =Q42/1.11^$T42 -> -3513513.5 | K75: New York-based | M75: Hong Kong–based
E76: =Q5/1.11^$T5 -> -21118416 | F76: =Q43/1.11^$T43 -> -21118416 | K76: 15 years | L76: 25 years | M76: 15 years | N76: 25 years
E77: =Q6/1.11^$T6 -> 4163111.8 | F77: =Q44/1.11^$T44 -> 4163111.8 | K77: =SUM(K88:K104) -> -8045291.1 | L77: =SUM(I88:I114) -> -7801561.2 | M77: =SUM(F74:F90) -> -1540471.7 | N77: =SUM(E74:E100) -> -426617.45
E78: =Q7/1.11^$T7 -> 3746402.5 | F78: =Q45/1.11^$T45 -> 3746402.5
E79: =Q8/1.11^$T8 -> 2979874.3 | F79: =Q46/1.11^$T46 -> 2979874.3
E80: =Q9/1.11^$T9 -> 2215377.9 | F80: =Q47/1.11^$T47 -> 2215377.9
E81: =Q10/1.11^$T10 -> 2113344.2 | F81: =Q48/1.11^$T48 -> 2113344.2
E82: =Q11/1.11^$T11 -> 1897904 | F82: =Q49/1.11^$T49 -> 1897904
E83: =Q12/1.11^$T12 -> 1708616.5 | F83: =Q50/1.11^$T50 -> 1708616.5
E84: =Q13/1.11^$T13 -> 1537391.4 | F84: =Q51/1.11^$T51 -> 1537391.4
E85: =Q14/1.11^$T14 -> 1177554.5 | F85: =Q52/1.11^$T52 -> 1177554.5
E86: =Q15/1.11^$T15 -> 1133416.5 | F86: =Q53/1.11^$T53 -> 1133416.5
E87: =Q16/1.11^$T16 -> 1016696 | F87: =Q54/1.11^$T54 -> 1016696
E88: =Q17/1.11^$T17 -> 911319.57 | F88: =Q55/1.11^$T55 -> 911319.57 | H88: DCF NY | I88: =P3/1.11^$T3 -> -3900000 | K88: =P41/1.11^$T41 -> -3900000
E89: =Q18/1.11^$T18 -> 818636.35 | F89: =Q56/1.11^$T56 -> 818636.35 | I89: =P4/1.11^$T4 -> -3513513.5 | K89: =P42/1.11^$T42 -> -3513513.5
E90: =Q19/1.11^$T19 -> 346727.48 | F90: =Q57/1.11^$T57 -> 1571812.1 | I90: =P5/1.11^$T5 -> -22288775 | K90: =P43/1.11^$T43 -> -22288775
E91: =Q20/1.11^$T20 -> 432190.24 | I91: =P6/1.11^$T6 -> 3101414.4 | K91: =P44/1.11^$T44 -> 3101414.4
E92: =Q21/1.11^$T21 -> 382166.32 | I92: =P7/1.11^$T7 -> 2791266.7 | K92: =P45/1.11^$T45 -> 2791266.7
E93: =Q22/1.11^$T22 -> 338340.91 | I93: =P8/1.11^$T8 -> 2257637.3 | K93: =P46/1.11^$T46 -> 2257637.3
E94: =Q23/1.11^$T23 -> 297131.44 | I94: =P9/1.11^$T9 -> 1672705.1 | K94: =P47/1.11^$T47 -> 1672705.1
E95: =Q24/1.11^$T24 -> 128035.06 | I95: =P10/1.11^$T10 -> 1643928 | K95: =P48/1.11^$T48 -> 1643928
E96: =Q25/1.11^$T25 -> 194227.97 | I96: =P11/1.11^$T11 -> 1477033 | K96: =P49/1.11^$T49 -> 1477033
E97: =Q26/1.11^$T26 -> 169057.6 | I97: =P12/1.11^$T12 -> 1329804.4 | K97: =P50/1.11^$T50 -> 1329804.4
E98: =Q27/1.11^$T27 -> 145673.71 | I98: =P13/1.11^$T13 -> 1196719 | K98: =P51/1.11^$T51 -> 1196719
E99: =Q28/1.11^$T28 -> 125342.23 | I99: =P14/1.11^$T14 -> 904332.76 | K99: =P52/1.11^$T52 -> 904332.76
E100: =Q29/1.11^$T29 -> 126773.41 | I100: =P15/1.11^$T15 -> 897834.87 | K100: =P53/1.11^$T53 -> 897834.87
I101: =P16/1.11^$T16 -> 805947.34 | K101: =P54/1.11^$T54 -> 805947.34
I102: =P17/1.11^$T17 -> 723024.81 | K102: =P55/1.11^$T55 -> 723024.81
I103: =P18/1.11^$T18 -> 649786.16 | K103: =P56/1.11^$T56 -> 649786.16
I104: =P19/1.11^$T19 -> 281915.16 | K104: =P57/1.11^$T57 -> 2205563.8
I105: =P20/1.11^$T20 -> 381101.71
I106: =P21/1.11^$T21 -> 338622.2
I107: =P22/1.11^$T22 -> 301161.76
I108: =P23/1.11^$T23 -> 266293.43
I109: =P24/1.11^$T24 -> 115858.48
I110: =P25/1.11^$T25 -> 186276.33
I111: =P26/1.11^$T26 -> 163941.81
I112: =P27/1.11^$T27 -> 143362.3
I113: =P28/1.11^$T28 -> 125301.68
I114: =P29/1.11^$T29 -> 145458.83
